[
  {
    "Name": "AB2B Boutique",
    "FormattedAddress": "27001 US HWY 19 N, Suite 2022, Clearwater, FL 33761",
    "Phone": "",
    "Email": "",
    "Website": "https://www.allbrides2be.com",
    "Tags": "Prom Dresses",
    "Lat": 28.0170595,
    "Lng": -82.7355688
  },
  {
    "Name": "The Dress Boutique",
    "FormattedAddress": "1348 Java Lane, Suite 105, Burlington, NC 27215",
    "Phone": "",
    "Email": "",
    "Website": "https://www.thedress.boutique",
    "Tags": "Prom Dresses",
    "Lat": 36.0683037,
    "Lng": -79.5160632
  },
  {
    "Name": "Wolsfelts Prom &amp; Tux",
    "FormattedAddress": "153 Ashland Ave., Aurora, IL 60505",
    "Phone": "",
    "Email": "",
    "Website": "https://www.wolsfeltsprom.com",
    "Tags": "Prom Dresses",
    "Lat": 41.7378239,
    "Lng": -88.3272485
  },
  {
    "Name": "Sash Prom",
    "FormattedAddress": "2150 Northwoods Blvd Suite 528-G, North Charleston, SC 29406",
    "Phone": "",
    "Email": "",
    "Website": "https://www.sashprom.com",
    "Tags": "Prom Dresses",
    "Lat": 32.9447225,
    "Lng": -80.0447602
  },
  {
    "Name": "Blue Violet Bridal &amp; Prom",
    "FormattedAddress": "32 High St., Westerly, RI 02891",
    "Phone": "",
    "Email": "",
    "Website": "https://www.bluevioletbridalandprom.com",
    "Tags": "Prom Dresses",
    "Lat": 41.378569,
    "Lng": -71.8304264
  },
  {
    "Name": "Angelique's",
    "FormattedAddress": "10130 Davenport Street NE, Suite 160, Blaine, MN 55449",
    "Phone": "",
    "Email": "",
    "Website": "https://www.angeliquesbridal.com",
    "Tags": "Prom Dresses",
    "Lat": 45.1541228,
    "Lng": -93.2306345
  },
  {
    "Name": "Merle Norman and More",
    "FormattedAddress": "1204 North City Avenue, Ripley, MS 38663",
    "Phone": "",
    "Email": "",
    "Website": "https://www.ripleyprom.com",
    "Tags": "Prom Dresses",
    "Lat": 34.7425797,
    "Lng": -88.9480077
  },
  {
    "Name": "Laura's Too",
    "FormattedAddress": "494 Route 3, Plattsburgh, NY 12901",
    "Phone": "",
    "Email": "",
    "Website": "https://laurastoo.com/",
    "Tags": "Prom Dresses",
    "Lat": 44.6969365,
    "Lng": -73.4962433
  },
  {
    "Name": "South's Specialty Clothiers",
    "FormattedAddress": "Boone Mall, 1180 Blowing Rock Rd., Boone, NC 28607",
    "Phone": "",
    "Email": "",
    "Website": "https://www.southsclothiers.com",
    "Tags": "Prom Dresses",
    "Lat": 36.2015574,
    "Lng": -81.6681577
  },
  {
    "Name": "A Pink Boutique",
    "FormattedAddress": "201 South Illinois St, Honart, IN 46352",
    "Phone": "",
    "Email": "",
    "Website": "https://apinkboutiqueshop.com",
    "Tags": "Prom Dresses",
    "Lat": 41.53387,
    "Lng": -87.2481699
  },
  {
    "Name": "MB Prom",
    "FormattedAddress": "123 South Urania Avenue, Greenburg, PA 15601",
    "Phone": "",
    "Email": "",
    "Website": "https://www.mbprom.com",
    "Tags": "Prom Dresses",
    "Lat": 40.3022833,
    "Lng": -79.5380539
  },
  {
    "Name": "Arden Bridal & Boutique",
    "FormattedAddress": "171 Westshore Plaza, Tampa, FL 33609",
    "Phone": "",
    "Email": "",
    "Website": "https://www.ardentampa.square.site/",
    "Tags": "Prom Dresses",
    "Lat": 27.9465863,
    "Lng": -82.5268818
  },
  {
    "Name": "My Formals",
    "FormattedAddress": "200 Old Rte 66 N, Lichfield, IL 62056",
    "Phone": "",
    "Email": "",
    "Website": "https://www.myformals.com",
    "Tags": "Prom Dresses",
    "Lat": 39.1760584,
    "Lng": -89.6662745
  },
  {
    "Name": "Loyce's",
    "FormattedAddress": "101 North Court Square, Waverly, TN 37185",
    "Phone": "",
    "Email": "",
    "Website": "https://www.loyces.business.site/",
    "Tags": "Prom Dresses",
    "Lat": 36.083468,
    "Lng": -87.794091
  },
  {
    "Name": "Elaine's Wedding Center",
    "FormattedAddress": "Elaine's Wedding Center, Green Bay, WI 54304",
    "Phone": "",
    "Email": "",
    "Website": "https://www.elainesweddingcenter.com/",
    "Tags": "Prom Dresses",
    "Lat": 44.4766082,
    "Lng": -88.0752792
  },
  {
    "Name": "Jarvis Couture",
    "FormattedAddress": "7264 Old Jacksonville Hwy, Tyler, TX 75703",
    "Phone": "",
    "Email": "",
    "Website": "https://www.jarviscouture.com",
    "Tags": "Prom Dresses",
    "Lat": 32.2670616,
    "Lng": -95.3406039
  },
  {
    "Name": "Sarah's Bridal Gallery",
    "FormattedAddress": "207 W. Clay Street, Mount Pleasant, IA 52641",
    "Phone": "",
    "Email": "",
    "Website": "https://www.sarahsbridalgallery.com",
    "Tags": "Prom Dresses",
    "Lat": 40.964872,
    "Lng": -91.5560521
  },
  {
    "Name": "Oconee Formal",
    "FormattedAddress": "1431 Capital Ave. Unit 107, Watkinssville, GA 30677",
    "Phone": "",
    "Email": "",
    "Website": "https://oconeeformal.com",
    "Tags": "Prom Dresses",
    "Lat": 33.8694846,
    "Lng": -83.4467842
  },
  {
    "Name": "Elaine's Wedding Center",
    "FormattedAddress": "410 N. Mall Drive, Appleton, WI 54913",
    "Phone": "",
    "Email": "",
    "Website": "https://www.elainesweddingcenter.com/",
    "Tags": "Prom Dresses",
    "Lat": 44.2656323,
    "Lng": -88.4728329
  },
  {
    "Name": "So Sweet Boutique",
    "FormattedAddress": "1665 Oviedo Mall Blvd., Oviedo, FL 32765",
    "Phone": "",
    "Email": "",
    "Website": "https://sosweetboutique.com",
    "Tags": "Prom Dresses",
    "Lat": 28.6634593,
    "Lng": -81.2335726
  },
  {
    "Name": "Christine's Bridal",
    "FormattedAddress": "138 Rt 12, Hartland, VT 05049",
    "Phone": "",
    "Email": "",
    "Website": "https://www.christinesbridal.com",
    "Tags": "Prom Dresses",
    "Lat": 43.5469393,
    "Lng": -72.4237134
  },
  {
    "Name": "Formals XO 2",
    "FormattedAddress": "160 Gulph Road, King of Prussia, PA 19406",
    "Phone": "",
    "Email": "",
    "Website": "https://www.formalsxo.com/",
    "Tags": "Prom Dresses",
    "Lat": 40.0892302,
    "Lng": -75.3859145
  },
  {
    "Name": "Rice N Ribbon",
    "FormattedAddress": "415 Main Street, Rockport, IN 47635",
    "Phone": "",
    "Email": "",
    "Website": "https://ricenribbon.com/",
    "Tags": "Prom Dresses",
    "Lat": 37.8834223,
    "Lng": -87.0490059
  },
  {
    "Name": "Black Tie and White Satin",
    "FormattedAddress": "507 North Broad Street, Fremont, NE 68025",
    "Phone": "",
    "Email": "",
    "Website": "https://www.blacktiewhitesatinbridal.com",
    "Tags": "Prom Dresses",
    "Lat": 41.4341214,
    "Lng": -96.4989561
  },
  {
    "Name": "Oh My Dress",
    "FormattedAddress": "4821 Shaopping Way, Corpus Christi, TX 78411",
    "Phone": "",
    "Email": "",
    "Website": "https://ohmy-dress.com",
    "Tags": "Prom Dresses",
    "Lat": 27.7134297,
    "Lng": -97.3719206
  },
  {
    "Name": "The Prom Shop",
    "FormattedAddress": "517 Frontage Road NW, Byron, MN 55920",
    "Phone": "",
    "Email": "",
    "Website": "https://thepromshop.net",
    "Tags": "Prom Dresses",
    "Lat": 44.0294276,
    "Lng": -92.6555894
  },
  {
    "Name": "Glitz & Gowns",
    "FormattedAddress": "225 Kent Stone Blvd., Alabaster, AL 35007",
    "Phone": "",
    "Email": "",
    "Website": "https://www.glitzandgowns.com",
    "Tags": "Prom Dresses",
    "Lat": 33.2143053,
    "Lng": -86.8232131
  },
  {
    "Name": "Lillian's Prom",
    "FormattedAddress": "19 East Main St., Peru, IN 46970",
    "Phone": "",
    "Email": "",
    "Website": "https://www.lilliansonline.com",
    "Tags": "Prom Dresses",
    "Lat": 40.7538285,
    "Lng": -86.0680029
  },
  {
    "Name": "Silver Spoon Formals",
    "FormattedAddress": "320 East Fourth Street, London, KY 40741",
    "Phone": "",
    "Email": "",
    "Website": "https://www.facebook.com/SilverSpoonFormals/",
    "Tags": "Prom Dresses",
    "Lat": 37.1301187,
    "Lng": -84.078515
  },
  {
    "Name": "Bridal Novias",
    "FormattedAddress": "6974 Gateway Blvd , El Paso, TX 79915",
    "Phone": "",
    "Email": "",
    "Website": "https://bridalnoviasboutique.com/",
    "Tags": "Prom Dresses",
    "Lat": 31.7718468,
    "Lng": -106.3800836
  },
  {
    "Name": "Carrie's Prom &amp; Tux",
    "FormattedAddress": "713 West Saint Germain St., Saint Cloud, MN 56301",
    "Phone": "",
    "Email": "",
    "Website": "https://www.carriespromtux.com ",
    "Tags": "Prom Dresses",
    "Lat": 45.5601204,
    "Lng": -94.161235
  },
  {
    "Name": "Maggies Bridal & Prom",
    "FormattedAddress": "2975 W Market St, Fairlawn, OH 44333, USA",
    "Phone": "",
    "Email": "",
    "Website": "",
    "Tags": "",
    "Lat": 41.128523099999995,
    "Lng": -81.6093375
  },
  {
    "Name": "RashawnRose Bridal and Prom",
    "FormattedAddress": "12920 W State Road 84, Davie FL 33325",
    "Phone": "",
    "Email": "",
    "Website": "https://rashawnrosebridal.com",
    "Tags": "Prom Dresses",
    "Lat": 26.115484,
    "Lng": -80.321388
  },
  {
    "Name": "The Bridal Connection / Prom Connection",
    "FormattedAddress": "708 N Ankeny Blvd, Ankeny, IA 50023",
    "Phone": "",
    "Email": "",
    "Website": " https://www.bridalconnectiondsm.com/",
    "Tags": "Prom Dresses",
    "Lat": 41.7376551,
    "Lng": -93.6014599
  },
  {
    "Name": "First Impressions",
    "FormattedAddress": "500 Madden Road, Suite C, Jacksonville, AR 72076",
    "Phone": "",
    "Email": "",
    "Website": "https://www.firstimpressionsprom.com",
    "Tags": "Prom Dresses",
    "Lat": 34.8892456,
    "Lng": -92.1036571
  },
  {
    "Name": "Unique Lady",
    "FormattedAddress": "25000 Southfield Rd, Southfield, MI 48075",
    "Phone": "",
    "Email": "",
    "Website": "https://uniquelady.com",
    "Tags": "Prom Dresses",
    "Lat": 42.4735929,
    "Lng": -83.22061
  },
  {
    "Name": "125 Bridal Prom & Tux",
    "FormattedAddress": "37 Plaistow Rd, Plaistow, NH 03865",
    "Phone": "",
    "Email": "",
    "Website": "https://www.125bridalboutique.com",
    "Tags": "Prom Dresses",
    "Lat": 42.8227643,
    "Lng": -71.103909
  },
  {
    "Name": "Fiancee Minot",
    "FormattedAddress": "6 Main St S, Minot, ND 58701, USA",
    "Phone": "",
    "Email": "",
    "Website": "",
    "Tags": "",
    "Lat": 48.2362646,
    "Lng": -101.2932458
  },
  {
    "Name": "Fancy Frocks Bridal Prom Tuxedo",
    "FormattedAddress": "820 Inlet Square Dr, Murrells Inlet, SC 29576",
    "Phone": "",
    "Email": "",
    "Website": "https://www.fancyfrocksbridal.com/",
    "Tags": "Prom Dresses",
    "Lat": 33.5816624,
    "Lng": -79.0215517
  },
  {
    "Name": "Best Bride Prom &amp; Tux - Merle Norman of Asheville",
    "FormattedAddress": "800 Fairview Rd. Suite A-1, Asheville, NC 28803",
    "Phone": "",
    "Email": "",
    "Website": "https://bestbridenc.com",
    "Tags": "Prom Dresses",
    "Lat": 35.5704168,
    "Lng": -82.5074949
  },
  {
    "Name": "Ashley Rene's",
    "FormattedAddress": "7135 Heritage Square Dr., Granger, IN 46530",
    "Phone": "",
    "Email": "",
    "Website": "https://www.ashleyrenespromandpageant.com",
    "Tags": "Prom Dresses",
    "Lat": 41.7255821,
    "Lng": -86.176209
  },
  {
    "Name": "Signatures Formal Boutique",
    "FormattedAddress": "1855 N. 25th st, Middlesboro, KY 40965",
    "Phone": "",
    "Email": "",
    "Website": "https://www.signaturesformal.com/",
    "Tags": "Prom Dresses",
    "Lat": 36.6235665,
    "Lng": -83.7057322
  },
  {
    "Name": "Cloud Nine Bridal Boutique",
    "FormattedAddress": "4711 N. University St., Peoria, IL 61614",
    "Phone": "",
    "Email": "",
    "Website": "https://www.cloudninepeopria.com",
    "Tags": "Prom Dresses",
    "Lat": 40.7449776,
    "Lng": -89.61308919999999
  },
  {
    "Name": "Anitra's",
    "FormattedAddress": "811 North 4th St., Monroe, LA 71201",
    "Phone": "",
    "Email": "",
    "Website": "https://www.anitraspromdresses.com",
    "Tags": "Prom Dresses",
    "Lat": 32.5098572,
    "Lng": -92.1203046
  },
  {
    "Name": "Michelle's Formal Wear",
    "FormattedAddress": "101 S Burwell Ave, Adel, GA 31620",
    "Phone": "",
    "Email": "",
    "Website": "https://www.michellesformalwear.net",
    "Tags": "Prom Dresses",
    "Lat": 31.1367305,
    "Lng": -83.4239978
  },
  {
    "Name": "Ella Blu",
    "FormattedAddress": "5410 N. Mesa, El Paso, TX 79912",
    "Phone": "",
    "Email": "",
    "Website": "https://ellablubridal.com/",
    "Tags": "Prom Dresses",
    "Lat": 31.8193786,
    "Lng": -106.5163572
  },
  {
    "Name": "CTO Prom &amp; Formal",
    "FormattedAddress": "7475 Douglas Blvd ste 102, Douglasville, GA 30135, USA",
    "Phone": "",
    "Email": "",
    "Website": "https://www.ctoprom.com/",
    "Tags": "Prom Dresses",
    "Lat": 33.7228829,
    "Lng": -84.7701038
  },
  {
    "Name": "Formals XO",
    "FormattedAddress": "Oxford Valley Mall, 2300 Lincoln Hwy, Longhorne, PA 19047",
    "Phone": "",
    "Email": "",
    "Website": "https://www.formalsxo.com/",
    "Tags": "Prom Dresses",
    "Lat": 40.1838453,
    "Lng": -74.8804078
  }
]